setup.py
guesstimator/__init__.py
guesstimator/guesstimator.py
guesstimator.egg-info/PKG-INFO
guesstimator.egg-info/SOURCES.txt
guesstimator.egg-info/dependency_links.txt
guesstimator.egg-info/requires.txt
guesstimator.egg-info/top_level.txt
test/__init__.py
test/test_sampy.py