Metadata-Version: 1.0
Name: guesstimator
Version: 0.0.2
Summary: Estimates the performance of a distributed system based on a sample set of data.
Home-page: https://github.com/bcoe/guesstimator
Author: Benjamin Coe
Author-email: ben@attachments.me
License: UNKNOWN
Platform: UNKNOWN
